_NRSur7dq2_utils.cpython-38-darwin.so
NRSur7dq2/NRSur7dq2.h5
NRSur7dq2/NRSur7dq2.py
NRSur7dq2/__init__.py
NRSur7dq2/harmonics.py
NRSur7dq2-1.0.6.dist-info/LICENSE.txt
NRSur7dq2-1.0.6.dist-info/METADATA
NRSur7dq2-1.0.6.dist-info/WHEEL
NRSur7dq2-1.0.6.dist-info/top_level.txt
NRSur7dq2-1.0.6.dist-info/RECORD
