Metadata-Version: 2.1
Name: NRSur7dq2
Version: 1.0.6
Summary: Package for evaluating the NRSur7dq2 surrogate model
Home-page: https://www.black-holes.org/surrogates/
Author: Jonathan Blackman
Author-email: jonathan.blackman.0@gmail.com
License: UNKNOWN
Platform: UNKNOWN
Requires-Dist: numpy
Requires-Dist: scipy
Requires-Dist: h5py
